pyfecto/__init__.py
pyfecto/app.py
pyfecto/collections.py
pyfecto/pyio.py
pyfecto/runtime.py
pyfecto-0.3.0.dist-info/LICENSE
pyfecto-0.3.0.dist-info/METADATA
pyfecto-0.3.0.dist-info/WHEEL
pyfecto-0.3.0.dist-info/RECORD
