Metadata-Version: 2.3
Name: pyfecto
Version: 0.3.0
Summary: A simple yet powerful library for handling effects and errors in Python
License: MIT
Author: fernanluyano
Requires-Python: >=3.11,<4.0
Classifier: License :: OSI Approved :: MIT License
Classifier: Programming Language :: Python :: 3
Classifier: Programming Language :: Python :: 3.11
Classifier: Programming Language :: Python :: 3.12
Classifier: Programming Language :: Python :: 3.13
Requires-Dist: gitpython (>=3.1.0,<4.0.0)
Requires-Dist: loguru (>=0.7.3,<0.8.0)
